pydynamo/__init__.py
pydynamo/core/__init__.py
pydynamo/core/delays.py
pydynamo/core/graph.py
pydynamo/core/parse_dynamo_functions.py
pydynamo/core/parse_equations.py
pydynamo/core/parse_system.py
pydynamo/core/plot_system.py
pydynamo/core/politics.py
pydynamo/core/psdsystem.py
pydynamo/core/specials.py
pydynamo/core/system.py
pydynamo/utilities/__init__.py
pydynamo/utilities/dynamo_converter.py
pydynamo/world2/__init__.py
pydynamo/world2/code_pydynamo_w2.py
pydynamo/world2/definitions_w2.json
pydynamo/world3/__init__.py
pydynamo/world3/code_pydynamo_w3.py
pydynamo/world3/data_world3.py
pydynamo/world3/definitions_w3.json
pydynamo/world3/get_definitions.py
pydynamo/world3/get_sectors.py
pydynamo/world3/plot_utils.py
pydynamo/world3/scenarios_limits_to_growth.py
pydynamo/world3/units_w3.json
pydynamo/world3/variable_definitions.json
pydynamo/world3/world3.py
pydynamo_w-0.0.3.dist-info/licenses/LICENSE
pydynamo_w-0.0.3.dist-info/METADATA
pydynamo_w-0.0.3.dist-info/WHEEL
pydynamo_w-0.0.3.dist-info/top_level.txt
pydynamo_w-0.0.3.dist-info/RECORD
