Metadata-Version: 2.4
Name: pydynamo-w
Version: 0.0.3
Summary: Pydynamo is a module to define, run and analyse system dynamics. I intially created it to play with the World3 model, which was written in DYNAMO, with Python.
Home-page: https://gitlab.inria.fr/abaucher/pydynamo/-/tree/package
Author: Achille Baucher
Author-email: achille.baucher@inria.fr
Project-URL: TP, https://gitlab.inria.fr/abaucher/pydynamo/
Classifier: License :: OSI Approved :: The Unlicense (Unlicense)
Classifier: Operating System :: OS Independent
Requires-Python: >=3.12
License-File: LICENSE
Requires-Dist: astunparse==1.6.3
Requires-Dist: matplotlib==3.10.7
Requires-Dist: networkx==3.5
Requires-Dist: numpy==2.3.4
Requires-Dist: pyvis==0.3.2
Dynamic: license-file
